yamlable/__init__.py
yamlable/_version.py
yamlable/base.py
yamlable/main.py
yamlable/py.typed
yamlable/yaml_objects.py
yamlable-1.1.1.dist-info/LICENSE
yamlable-1.1.1.dist-info/METADATA
yamlable-1.1.1.dist-info/WHEEL
yamlable-1.1.1.dist-info/top_level.txt
yamlable-1.1.1.dist-info/RECORD
