Metadata-Version: 2.1
Name: yamlable
Version: 1.1.1
Summary: A thin wrapper of PyYaml to convert Python objects to YAML and back.
Home-page: https://github.com/smarie/python-yamlable
Download-URL: https://github.com/smarie/python-yamlable/tarball/1.1.1
Author: Sylvain MARIE <sylvain.marie@se.com>
Maintainer: Sylvain MARIE <sylvain.marie@se.com>
License: BSD 3-Clause
Keywords: yaml file parsing parse load dump read write object oo oriented codec format plugin pyYaml
Platform: UNKNOWN
Classifier: Development Status :: 5 - Production/Stable
Classifier: Intended Audience :: Developers
Classifier: License :: OSI Approved :: BSD License
Classifier: Topic :: Software Development :: Libraries :: Python Modules
Classifier: Programming Language :: Python
Classifier: Programming Language :: Python :: 2
Classifier: Programming Language :: Python :: 2.7
Classifier: Programming Language :: Python :: 3
Classifier: Programming Language :: Python :: 3.5
Classifier: Programming Language :: Python :: 3.6
Classifier: Programming Language :: Python :: 3.7
Classifier: Programming Language :: Python :: 3.8
Classifier: Programming Language :: Python :: 3.9
License-File: LICENSE
Requires-Dist: PyYaml
Requires-Dist: six
